falco/__init__.py
falco/_globals.py
falco/check.py
falco/ctrl.py
falco/dftidefs.py
falco/dm.py
falco/est.py
falco/fftutils.py
falco/hexsegmirror.py
falco/hlc.py
falco/imaging.py
falco/mask.py
falco/mkl_fft.py
falco/plot.py
falco/prop.py
falco/setup.py
falco/thinfilm.py
falco/util.py
falco/wfsc.py
falco/zern.py
falco/config/ModelParameters.py
falco/config/__init__.py
falco/config/asdfModelVariables.py
falco/config/init_from_mat.py
falco/model/__init__.py
falco/model/jacobians.py
falco/model/models.py
falco/model/models_b.py
pyfalco-3.0.2.dist-info/LICENSE
pyfalco-3.0.2.dist-info/METADATA
pyfalco-3.0.2.dist-info/WHEEL
pyfalco-3.0.2.dist-info/top_level.txt
pyfalco-3.0.2.dist-info/RECORD
